lions/__init__.py
lions/errors.py
lions/lmsg.py
lions/main.py
lions/yaml_parser.py
lions/cpp_gen/__init__.py
lions/cpp_gen/cpp_generator.py
lions/cpp_gen/templates/lions.cpp.jinja
lions/cpp_gen/templates/lions.hpp.jinja
lions/cpp_gen/templates/msg.cpp.jinja
lions/cpp_gen/templates/msg.hpp.jinja
lions/js_gen/__init__.py
lions/js_gen/js_generator.py
lions/ts_gen/__init__.py
lions/ts_gen/ts_generator.py
lionsc/__init__.py
lionsc/errors.py
lionsc/lmsg.py
lionsc/main.py
lionsc/yaml_parser.py
lionsc/code_generation/__init__.py
lionsc/code_generation/c/__init__.py
lionsc/code_generation/c/c_generator.py
lionsc/code_generation/c/templates/__init__.py
lionsc/code_generation/cpp/__init__.py
lionsc/code_generation/cpp/cpp_generator.py
lionsc/code_generation/cpp/templates/__init__.py
lionsc/code_generation/cpp/templates/lions.cpp.jinja
lionsc/code_generation/cpp/templates/lions.hpp.jinja
lionsc/code_generation/cpp/templates/msg.cpp.jinja
lionsc/code_generation/cpp/templates/msg.hpp.jinja
lionsc/code_generation/js/__init__.py
lionsc/code_generation/js/js_generator.py
lionsc/code_generation/js/templates/__init__.py
lionsc/code_generation/js/templates/lions.js.jinja
lionsc/code_generation/js/templates/msg.js.jinja
lionsc/code_generation/python/__init__.py
lionsc/code_generation/python/python_generator.py
lionsc/code_generation/python/templates/__init__.py
lionsc/code_generation/python/templates/lions.py.jinja
lionsc/code_generation/python/templates/msg.py.jinja
lionsc/code_generation/ts/__init__.py
lionsc/code_generation/ts/ts_generator.py
lionsc/code_generation/ts/templates/__init__.py
lionsc/code_generation/ts/templates/lions.ts.jinja
lionsc/code_generation/ts/templates/msg.ts.jinja
tests/__init__.py
tests/test_c_gen.py
tests/test_cpp_gen.py
tests/test_js_gen copy.py
tests/test_js_gen.py
tests/test_lmsg.py
tests/test_python_gen.py
tests/test_ts_gen.py
tests/test_yaml_parser.py
lionsc-2.1.0.dist-info/LICENSE
lionsc-2.1.0.dist-info/METADATA
lionsc-2.1.0.dist-info/WHEEL
lionsc-2.1.0.dist-info/entry_points.txt
lionsc-2.1.0.dist-info/top_level.txt
lionsc-2.1.0.dist-info/RECORD
